{"modID":"MOP","description":"<color=yellow><b>Modern Optimization Plugin</b></color> is the ultimate performance enhancing project for My Summer Car.\r\n\r\nThe ultimate performance-enhancing project for My Summer Car. Quickly and easily improve FPS of MSC!\r\n\r\n<color=yellow><b>Credits</b></color> \r\n\r\n- Krutonium - original KruFPS creator, and the KruFPS contributors: \r\n    - RedJohn260 \r\n    - EPS \r\n- Est_Nbmstr - for clever name idea \r\n- FESilencer - for helping me figure out how PlayMaker actions work","links":{"nexusLink":"https://www.nexusmods.com/mysummercar/mods/146/","rdLink":"","githubLink":"https://github.com/Athlon007/MOP"},"icon":{"iconFileName":"MOP_1658136874.png","isIconRemote":true},"minimumRequirements":{"MSCLoaderVer":"1.2.3","MSCbuildID":5119897,"disableIfVer":true},"modConflicts":{"modIDs":"KruFPS,ImproveFPS,OptimizeMSC,ZZDisableAll,DisableAll","customMessage":"MOP is not compatible with other FPS improving mods.","disableIfConflict":true},"requiredMods":{"modID":"","minVer":"","customMessage":""},"sign":"3F4677E9AA5B545C75EFAFC0F6F5C24A","sid_sign":"e606284cb072db180738daa0e92f81e93ccd8e20","type":4,"msg":"","rev":6}